Chessnut/__init__.py
Chessnut/board.py
Chessnut/game.py
Chessnut/moves.py
Chessnut/tests/__init__.py
Chessnut/tests/test_board.py
Chessnut/tests/test_game.py
Chessnut/tests/test_moves.py
Chessnut-0.4.1.dist-info/METADATA
Chessnut-0.4.1.dist-info/WHEEL
Chessnut-0.4.1.dist-info/top_level.txt
Chessnut-0.4.1.dist-info/RECORD
