Metadata-Version: 2.1
Name: Chessnut
Version: 0.4.1
Summary: A basic chess model to imports/export FEN & finds moves.
Home-page: https://github.com/cgearhart/Chessnut
Author: Chris Gearhart
Author-email: chris@gearley.com
License: UNLICENSE
Keywords: chess
